listthedocs/__init__.py
listthedocs/attr_utils.py
listthedocs/client.py
listthedocs/commands.py
listthedocs/datetime_utils.py
listthedocs/controllers/__init__.py
listthedocs/controllers/errors.py
listthedocs/controllers/exceptions.py
listthedocs/controllers/projects.py
listthedocs/controllers/security.py
listthedocs/controllers/users.py
listthedocs/controllers/utils.py
listthedocs/controllers/webui.py
listthedocs/database/__init__.py
listthedocs/database/database.py
listthedocs/database/exceptions.py
listthedocs/entities/__init__.py
listthedocs/entities/entity.py
listthedocs/entities/project.py
listthedocs/entities/user.py
listthedocs/entities/utils.py
listthedocs/static/styles/extra.css
listthedocs/templates/base.html
listthedocs/templates/index.html
listthedocs-2.0.1.dist-info/LICENSE.txt
listthedocs-2.0.1.dist-info/METADATA
listthedocs-2.0.1.dist-info/WHEEL
listthedocs-2.0.1.dist-info/top_level.txt
listthedocs-2.0.1.dist-info/RECORD
