Metadata-Version: 2.1
Name: listthedocs
Version: 2.0.1
Summary: List your documentations
Home-page: https://github.com/allebacco/listthedocs
Author: Alessandro Bacchini
Author-email: allebacco@gmail.com
License: UNKNOWN
Platform: UNKNOWN
Classifier: Programming Language :: Python :: 3
Classifier: Development Status :: 5 - Production/Stable
Classifier: License :: OSI Approved :: MIT License
Classifier: Operating System :: OS Independent
Classifier: Environment :: Web Environment
Classifier: Intended Audience :: Developers
Classifier: Topic :: Documentation
Classifier: Topic :: Software Development :: Documentation
Requires-Python: >=3.5
Requires-Dist: natsort
Requires-Dist: requests
Requires-Dist: attrs
Requires-Dist: python-dateutil
Requires-Dist: Flask-SQLAlchemy
Requires-Dist: Flask
